Metadata-Version: 2.4
Name: pybanksy
Version: 1.3.4
Summary: BANKSY: Spatial Clustering Algorithm that Unifies Cell-Typing and Tissue Domain Segmentation. It reduces the spatial clustering problem to a previously solved problem--generic graph based clustering--by augmenting transcriptional signatures with transcriptional features averaged over spatial microenvironments.
Author-email: Nigel Chou <Nigel_Chou@gis.a-star.edu.sg>, Yifei Yue <yifei1021@gmail.com>, Vipul Singhal <vs@alumni.caltech.edu>
Maintainer-email: Vipul Singhal <vs@alumni.caltech.edu>
License: GPL-3.0
Project-URL: Homepage, https://github.com/prabhakarlab/Banksy_py
Project-URL: Documentation, https://github.com/prabhakarlab/Banksy_py/blob/main/README.md
Project-URL: Repository, https://github.com/prabhakarlab/Banksy_py
Project-URL: Bug Tracker, https://github.com/prabhakarlab/Banksy_py/issues
Project-URL: Publication, https://www.nature.com/articles/s41588-024-01664-3
Keywords: spatial transcriptomics,clustering,single-cell,spatial omics,bioinformatics,BANKSY
Classifier: Development Status :: 4 - Beta
Classifier: Intended Audience :: Science/Research
Classifier: Topic :: Scientific/Engineering :: Bio-Informatics
Classifier: License :: OSI Approved :: GNU General Public License v3 (GPLv3)
Classifier: Programming Language :: Python :: 3
Classifier: Programming Language :: Python :: 3.8
Classifier: Programming Language :: Python :: 3.9
Classifier: Programming Language :: Python :: 3.10
Classifier: Programming Language :: Python :: 3.11
Classifier: Programming Language :: Python :: 3.12
Requires-Python: <3.13,>=3.8
License-File: LICENSE.md
Requires-Dist: anndata>=0.8.0
Requires-Dist: numpy<2.0,>=1.21
Requires-Dist: scipy>=1.7.0
Requires-Dist: pandas>=1.3.0
Requires-Dist: scikit-learn>=1.0.0
Requires-Dist: matplotlib>=3.4.0
Requires-Dist: seaborn>=0.11.0
Requires-Dist: scanpy>=1.8.0
Requires-Dist: umap-learn>=0.5.0
Requires-Dist: python-igraph>=0.9.0
Requires-Dist: leidenalg>=0.8.0
Requires-Dist: h5py>=3.0.0
Provides-Extra: notebooks
Requires-Dist: jupyter>=1.0; extra == "notebooks"
Requires-Dist: ipykernel>=6.0; extra == "notebooks"
Provides-Extra: dev
Requires-Dist: pytest>=7.0; extra == "dev"
Requires-Dist: jupyter>=1.0; extra == "dev"
Requires-Dist: ipykernel>=6.0; extra == "dev"
Provides-Extra: mclust
Requires-Dist: rpy2>=3.4.0; extra == "mclust"
Provides-Extra: all
Requires-Dist: jupyter>=1.0; extra == "all"
Requires-Dist: ipykernel>=6.0; extra == "all"
Requires-Dist: pytest>=7.0; extra == "all"
Requires-Dist: rpy2>=3.4.0; extra == "all"
Dynamic: license-file
